{
  "id": "sk_164",
  "archetype": "堕落与沉沦",
  "title": "剑客的黄昏",
  "logline": "一位恪守侠义的剑客，为守护所爱之人，被迫向权力低头，在江湖规则的侵蚀下逐渐迷失本心。",
  "style_tags": [
    "江湖",
    "古代",
    "严肃文学",
    "心理现实主义"
  ],
  "ending": "open",
  "stakes": "信念",
  "actors": [
    "主角",
    "爱人",
    "家族",
    "敌对势力",
    "导师"
  ],
  "beats": [
    {
      "id": 1,
      "name": "平静的日常",
      "desc": "剑客在江南小镇过着清贫但心安的生活，每日练剑、教孩童识字，与爱人相守。他坚信手中的剑只为守护道义与弱者。"
    },
    {
      "id": 2,
      "name": "阴影的迫近",
      "desc": "爱人的家族因卷入朝堂斗争而面临灭顶之灾。敌对势力——一个庞大而腐败的江湖帮派，递来了招揽与威胁并存的信函。"
    },
    {
      "id": 3,
      "name": "第一次妥协",
      "desc": "为了换取家族暂时的安全，剑客违背原则，为帮派完成了一件不光彩的‘小事’。他安慰自己这只是权宜之计，内心却已裂开缝隙。"
    },
    {
      "id": 4,
      "name": "导师的警示",
      "desc": "隐居的恩师察觉其变化，痛心告诫：‘江湖如染缸，沾一次，便洗不净。’剑客辩解是为了守护，却不敢直视恩师的眼睛。"
    },
    {
      "id": 5,
      "name": "泥沼中的沉溺",
      "desc": "帮派的要求越来越过分，剑客的‘帮忙’从一次变为常态。他开始熟练地运用暴力与恐吓，并从中获得扭曲的掌控感与资源。"
    },
    {
      "id": 6,
      "name": "爱人的疏离",
      "desc": "爱人察觉到他眼神的冰冷与手段的狠厉，感到陌生与恐惧。昔日的温情被沉默与隔阂取代，守护的初衷变得面目全非。"
    },
    {
      "id": 7,
      "name": "自我的审视",
      "desc": "某个深夜，他看着镜中佩着华贵剑鞘的自己，突然想不起最初那把朴素铁剑的模样。恐惧与麻木交织，他分不清哪个更真实。"
    },
    {
      "id": 8,
      "name": "无可挽回",
      "desc": "帮派命他除掉一个知晓内情的正直故人。他最终完成了任务，手上沾了不该沾的血。那一刻，他感到某种一直紧绷的东西彻底断了。"
    },
    {
      "id": 9,
      "name": "黄昏独行",
      "desc": "他拥有了权势与财富，爱人却已离去，恩师与之断绝关系。他独自站在高楼，望着熟悉的江湖夕阳，不知自己是谁，也不知该去向何方。"
    }
  ],
  "tension_curve": [
    0.15,
    0.3,
    0.4,
    0.5,
    0.65,
    0.7,
    0.75,
    0.8,
    0.78
  ],
  "themes": [
    "信念的腐蚀",
    "守护的异化",
    "自由意志的困境",
    "人与环境的互相塑造"
  ]
}