{
  "id": "sk_166",
  "archetype": "寻找真相",
  "title": "江湖夜雨十年灯",
  "logline": "一位退隐的侠客因一封故人遗书，被迫重访过往，在记忆与传说的迷雾中，寻找一个可能并不存在的真相。",
  "style_tags": [
    "江湖",
    "古代",
    "严肃文学",
    "心理现实主义"
  ],
  "ending": "open",
  "stakes": "信念",
  "actors": [
    "主角",
    "导师",
    "盟友",
    "爱人",
    "家族",
    "敌对势力"
  ],
  "beats": [
    {
      "id": 1,
      "name": "旧信惊澜",
      "desc": "主角收到一封来自已故恩师的信，信中暗示当年导致师门分崩离析的惨案另有隐情。平静的退隐生活被撕开一道裂缝，过往的尘埃开始浮动。"
    },
    {
      "id": 2,
      "name": "重访故地",
      "desc": "主角回到阔别多年的旧日江湖。景物依稀，人事已非。昔日的盟友与敌对势力都已面目模糊，记忆本身成为第一个需要审视的对象。"
    },
    {
      "id": 3,
      "name": "沉默的盟友",
      "desc": "找到一位尚在人世的旧日盟友，对方却对往事讳莫如深，只以疲惫的眼神暗示主角放手。真相的价值与搅动死水的代价，开始在心中拉锯。"
    },
    {
      "id": 4,
      "name": "爱人的证词",
      "desc": "与离散多年的爱人重逢。她的叙述与主角的记忆存在微妙而关键的偏差。爱情滤镜下的往事，与冷酷现实的可能样貌，产生剧烈冲突。"
    },
    {
      "id": 5,
      "name": "家族的阴影",
      "desc": "深入调查触及主角自身家族的隐秘利益与当年在事件中的暧昧立场。寻找外部真相，演变为对自身血脉与道德源头的拷问。"
    },
    {
      "id": 6,
      "name": "导师的遗产",
      "desc": "发现导师留下的一些私密手札，其中充满自我怀疑与矛盾的记录。原本被视为绝对权威的“控诉者”，其立场也变得摇摆不定。"
    },
    {
      "id": 7,
      "name": "敌意的迷雾",
      "desc": "来自敌对势力的阻挠并非激烈的厮杀，而是散布更多相互矛盾的流言与伪造的证据。真相的空间被彻底污染，任何结论都显得武断。"
    },
    {
      "id": 8,
      "name": "内心的审判",
      "desc": "主角意识到，或许永远无法获得一个确凿的外部真相。重点转向内心：自己为何执着于此？是为了正义，还是为了给自身的痛苦找一个确切的归因？"
    },
    {
      "id": 9,
      "name": "雨夜独行",
      "desc": "没有揭晓谜底，没有惩恶扬善。主角带着更多疑问、些许释然与永恒的缺憾，再次离开江湖。雨夜中，灯笼微光只照亮脚下三步之遥。"
    }
  ],
  "tension_curve": [
    0.2,
    0.3,
    0.4,
    0.5,
    0.6,
    0.65,
    0.7,
    0.75,
    0.4
  ],
  "themes": [
    "记忆的不可靠性",
    "道德相对主义",
    "执念与放下"
  ]
}