{
  "id": "sk_216",
  "archetype": "寻找真相",
  "title": "旧宅里的沉默",
  "logline": "一位中年作家回到祖宅整理遗物，在日记与旧信中，逐渐揭开家族荣耀背后被刻意遗忘的背叛与牺牲。",
  "style_tags": [
    "现代",
    "家族",
    "严肃文学",
    "心理现实主义"
  ],
  "ending": "triumph",
  "stakes": "荣耀",
  "actors": [
    "主角",
    "家族",
    "导师",
    "盟友"
  ],
  "beats": [
    {
      "id": 1,
      "name": "重返",
      "desc": "主角回到空置多年的祖宅，空气中弥漫着灰尘与旧时光的气味。他表面上是来整理遗物，内心却逃避着某种未明言的愧疚与疏离。"
    },
    {
      "id": 2,
      "name": "触碰",
      "desc": "在书房角落发现上锁的檀木匣。触碰它时，指尖传来冰凉的触感，仿佛直接触碰到了家族历史那沉默而坚硬的表皮。"
    },
    {
      "id": 3,
      "name": "裂隙",
      "desc": "通过一位远房叔公（导师）含糊的指点，打开了匣子。里面是祖父的日记与几封字迹娟秀的信，第一页写着：“荣耀是件需要不断缝补的衣裳。”"
    },
    {
      "id": 4,
      "name": "对照",
      "desc": "日记里描绘的家族创业史光辉体面，而信件却来自一位被家族生意逼至破产的故人，言辞恳切绝望。两种叙述开始在他脑中撕扯。"
    },
    {
      "id": 5,
      "name": "质询",
      "desc": "他向尚健在但已糊涂的祖母求证，老人时而微笑回忆荣光，时而因某个名字陷入长久的沉默与泪水中。真相变得更加模糊。"
    },
    {
      "id": 6,
      "name": "共谋",
      "desc": "他找到那位故人的后代（盟友），对方家族同样守着一段被损害的回忆。两人对坐无言，共享着一种沉重的、近乎羞耻的理解。"
    },
    {
      "id": 7,
      "name": "重估",
      "desc": "他独自在祖宅度过一夜，审视着墙上每一张荣耀的合影。那些笑容在他看来，逐渐变成了精心维持的、集体性的表演。"
    },
    {
      "id": 8,
      "name": "承纳",
      "desc": "他没有公开揭露什么，也没有激烈的决裂。他决定将日记与信件一同封存回原处，但自己内心对‘家族’的定义已彻底崩塌与重建。"
    },
    {
      "id": 9,
      "name": "离去",
      "desc": "他锁上祖宅大门，阳光刺眼。他带走的不再是愧疚，而是一种平静的清醒：真正的荣耀，或许始于承认荣耀之下的阴影。"
    }
  ],
  "tension_curve": [
    0.2,
    0.3,
    0.4,
    0.55,
    0.6,
    0.65,
    0.7,
    0.5,
    0.3
  ],
  "themes": [
    "记忆的不可靠性",
    "荣耀的代价",
    "个人与历史的和解"
  ]
}