{
  "id": "sk_341",
  "archetype": "寻找真相",
  "title": "江湖夜雨十年灯",
  "logline": "一名退隐的江湖客，为查明挚友离奇死亡的真相，被迫重入纷争，却发现真相指向自己遗忘的过去。",
  "style_tags": [
    "江湖",
    "悬疑",
    "严肃文学",
    "心理现实主义"
  ],
  "ending": "tragedy",
  "stakes": "生命",
  "actors": [
    "主角",
    "导师",
    "盟友",
    "爱人",
    "家族",
    "敌对势力"
  ],
  "beats": [
    {
      "id": 1,
      "name": "平静的裂痕",
      "desc": "退隐多年的主角收到故友暴毙的噩耗，表面是意外，但一封语焉不详的遗书，像一枚石子投入死水，搅动了他刻意维持的平静。他感到一种空洞的召唤，而非愤怒。"
    },
    {
      "id": 2,
      "name": "重返旧地",
      "desc": "他回到阔别已久的江湖小镇，物是人非。空气中弥漫着熟悉的危险与谎言。盟友提供线索，暗示死亡与一个庞大的秘密有关，这秘密与他被遗忘的家族渊源纠缠不清。"
    },
    {
      "id": 3,
      "name": "导师的警示",
      "desc": "昔日的导师，一位看透世情的老人，警告他真相如同深渊，凝视过久自身也将被吞噬。导师的话语充满矛盾，既指引方向，又暗示停止。主角在求知与自保间摇摆。"
    },
    {
      "id": 4,
      "name": "爱人的疏离",
      "desc": "他的爱人，因他重涉险境而恐惧，更因他眼中日益增长的偏执与陌生而疏远。温情成为负担，提醒他所珍视的生活正因他的追寻而碎裂。他感到双重的失去。"
    },
    {
      "id": 5,
      "name": "记忆的迷雾",
      "desc": "调查指向一段他自己也模糊的过去，可能是家族参与的某桩隐秘罪行。敌对势力的阴影浮现，并非具体的恶人，而是弥漫的系统性压迫。他开始怀疑自己的动机与清白。"
    },
    {
      "id": 6,
      "name": "盟友的代价",
      "desc": "唯一信任的盟友因协助他而遭遇不测，生死未卜。主角陷入深深的自责，他的追寻如同瘟疫，感染并摧毁靠近他的人。行动变得迟缓，充满犹豫。"
    },
    {
      "id": 7,
      "name": "直面虚无",
      "desc": "核心证据揭示，挚友之死或许源于一个无意义的误会，或是更大阴谋中微不足道的一环。没有明确的凶手，只有一连串的偶然与冷漠。真相非但不解渴，反而加剧了存在的荒诞感。"
    },
    {
      "id": 8,
      "name": "无可挽回",
      "desc": "在试图做最后了断时，他无意中触发了连锁反应，导致爱人或无辜者受害。他成了自己曾想对抗的毁灭力量的一部分。江湖的雨冰冷，洗净不了任何血迹。"
    },
    {
      "id": 9,
      "name": "灯灭人独",
      "desc": "他知晓了一切，却失去了所有。真相没有带来解脱，只有永恒的负重。他选择留在江湖的阴影里，成为另一个传说，一个关于追寻本身即为惩罚的警示。雨继续下着。"
    }
  ],
  "tension_curve": [
    0.2,
    0.35,
    0.45,
    0.5,
    0.65,
    0.7,
    0.75,
    0.8,
    0.85
  ],
  "themes": [
    "记忆与遗忘",
    "道德责任的边界",
    "追寻的虚无",
    "个人与系统的对抗"
  ]
}