{
  "id": "sk_374",
  "archetype": "跨越阶级的爱",
  "title": "玻璃幕墙与旧砖墙",
  "logline": "一个来自旧城区的青年与富家女相爱，在家族压力与自我怀疑中，他们的爱情逐渐被现实磨蚀。",
  "style_tags": [
    "家族",
    "现代",
    "严肃文学",
    "心理现实主义"
  ],
  "ending": "bittersweet",
  "stakes": "信念",
  "actors": [
    "主角",
    "爱人",
    "家族",
    "导师",
    "盟友"
  ],
  "beats": [
    {
      "id": 1,
      "name": "偶然的相遇",
      "desc": "在旧城区一家独立书店，出身贫寒的图书管理员主角，为前来寻找绝版书的富家女爱人指路。一场突如其来的雨将他们困在店内，在书籍与雨声的掩护下，他们开始了第一次深入的交谈。"
    },
    {
      "id": 2,
      "name": "试探的靠近",
      "desc": "他们开始秘密约会，地点总是选在城市的边缘地带，试图逃离各自的身份标签。主角感到一种不真实的眩晕，爱人的世界对他既是诱惑也是压迫，他既渴望融入，又本能地抗拒。"
    },
    {
      "id": 3,
      "name": "闯入的异域",
      "desc": "爱人坚持带主角参加一场她圈内的私人聚会。主角穿着借来的不合身西装，在觥筹交错间感到彻底的失语与孤立。他像一个观察者，冷静地记录着这个世界的浮华与空洞，内心却备受煎熬。"
    },
    {
      "id": 4,
      "name": "无声的警告",
      "desc": "爱人的家族并未激烈反对，而是以礼貌的疏远和偶尔提及的门当户对例子，施加着柔性的压力。主角自己的寡母则终日忧心忡忡，沉默地表达着对这段关系的不安与预见性的悲哀。"
    },
    {
      "id": 5,
      "name": "导师的冷光",
      "desc": "主角在社区大学的一位哲学导师，一位看透世情的老者，并未给出建议，只是讲述了一个关于‘玻璃天花板’与‘内心地板’的寓言。他的话像一面镜子，让主角更清晰地看见自己的处境与局限。"
    },
    {
      "id": 6,
      "name": "盟友的溃散",
      "desc": "主角唯一知情的旧日好友，起初支持他，但在目睹主角因这段关系变得日益敏感、痛苦和疏离后，两人爆发争吵。盟友指责主角变得陌生，这场决裂让主角失去了最后的锚点。"
    },
    {
      "id": 7,
      "name": "妥协的尝试",
      "desc": "主角试图通过疯狂工作与学习来跨越那道无形的鸿沟，结果身心俱疲。爱人则尝试融入主角的简朴生活，却总在不经意间流露出习惯性的优越感。两人都感到一种深沉的无力。"
    },
    {
      "id": 8,
      "name": "静默的崩解",
      "desc": "没有激烈的争吵，只有日益增长的疲惫与沉默。在一个平常的黄昏，他们并肩坐在初次相遇的书店门口，看着夕阳将玻璃幕墙和旧砖墙染成同样的金色，却都知道有些东西已经无法回去。"
    },
    {
      "id": 9,
      "name": "余烬与回响",
      "desc": "他们平静地分手。主角回到原有的生活轨道，但内心已被永久地改变，对爱与阶级有了更复杂、更悲悯的理解。偶尔，他会收到爱人从远方寄来的明信片，上面只有风景，没有字。"
    }
  ],
  "tension_curve": [
    0.2,
    0.35,
    0.5,
    0.6,
    0.65,
    0.7,
    0.75,
    0.8,
    0.6
  ],
  "themes": [
    "阶级的隐形壁垒",
    "自我认同的危机",
    "爱情作为幻象与真实",
    "现代社会的疏离"
  ]
}