{
  "id": "sk_444",
  "archetype": "师徒传承",
  "title": "宫墙下的授业",
  "logline": "一位宫廷画师在权力倾轧中，被迫在艺术传承与政治忠诚间做出选择，最终发现两者皆已面目全非。",
  "style_tags": [
    "架空",
    "宫廷",
    "严肃文学",
    "心理现实主义"
  ],
  "ending": "open",
  "stakes": "自由",
  "actors": [
    "主角",
    "导师",
    "盟友",
    "家族",
    "敌对势力"
  ],
  "beats": [
    {
      "id": 1,
      "name": "承平授业",
      "desc": "主角作为宫廷画院学徒，在导师的庇护下，沉浸于纯粹的艺术世界。导师传授的不仅是技法，更是‘画以载道’的古老信条。宫墙外的风雨，似乎与这方画室无关。"
    },
    {
      "id": 2,
      "name": "暗流初现",
      "desc": "一场突如其来的宫廷审查，导师的一幅旧作被指隐含‘不敬’。主角第一次感受到画纸的重量，也初次窥见导师眼中深藏的忧虑与沉默。"
    },
    {
      "id": 3,
      "name": "被迫的站队",
      "desc": "敌对势力，一位权势煊赫的宦官，向主角递出橄榄枝，要求其以画笔‘记录’（实为构陷）某位失势的皇族。家族的安危被悄然置于天平一端。"
    },
    {
      "id": 4,
      "name": "导师的黄昏",
      "desc": "导师在病榻上，气息微弱地讲述自己年轻时类似的困境与妥协。没有给出明确的答案，只有一声漫长的叹息，和一句‘笔在你手，路在你心’的呓语。"
    },
    {
      "id": 5,
      "name": "扭曲的临摹",
      "desc": "主角开始执行宦官的任务。他试图在奉命之作中藏入一丝真实的笔触，却发现每一次落笔，都在背叛导师传授的‘真’，也在扭曲自己眼中的‘实’。"
    },
    {
      "id": 6,
      "name": "盟友的警示",
      "desc": "一位同为画师、知晓内情的盟友，私下找到主角，暗示其画作已成为政治斗争的利器。盟友自身亦在恐惧中挣扎，劝诫与自保的言辞交织，充满矛盾。"
    },
    {
      "id": 7,
      "name": "家族的重量",
      "desc": "家族来信，感念主角在宫中的‘作为’带来的荫庇。字里行间的欣慰，像冰冷的锁链，将他捆绑在已选择的道路上。艺术与亲情，皆成重负。"
    },
    {
      "id": 8,
      "name": "无声的崩塌",
      "desc": "构陷成功，政敌倒台。主角获得嘉奖，却再也无法提笔作画。他看着自己那双被赞誉的手，只觉得它们沾满了看不见的、洗不掉的墨污。"
    },
    {
      "id": 9,
      "name": "空白的未来",
      "desc": "主角独自站在空旷的画院里，面前是雪白的画纸。导师已逝，盟友疏远，家族满足。他不知该画什么，也不知为何而画。未来如同这纸，一片刺目的空白。"
    }
  ],
  "tension_curve": [
    0.2,
    0.35,
    0.5,
    0.55,
    0.65,
    0.7,
    0.75,
    0.8,
    0.6
  ],
  "themes": [
    "艺术与权力的共谋",
    "传承的异化与背叛",
    "沉默中的道德崩解"
  ]
}