{
  "id": "sk_493",
  "archetype": "双重身份",
  "title": "镜中人与守夜者",
  "logline": "一位必须在夜间猎杀同胞以维持城市和平的混血异族，在爱上一位人类后，其双重身份带来的撕裂感将他推向崩溃边缘。",
  "style_tags": [
    "现代",
    "奇幻",
    "严肃文学",
    "心理现实主义"
  ],
  "ending": "pyrrhic",
  "stakes": "荣耀",
  "actors": [
    "主角",
    "爱人",
    "家族",
    "敌对势力"
  ],
  "beats": [
    {
      "id": 1,
      "name": "日常的裂痕",
      "desc": "主角作为城市守夜者，白天是温和的档案管理员，夜晚则追捕潜入的异族。他熟练地切换身份，但镜中自己的倒影开始显得陌生，一种缓慢的厌倦在心底滋生。"
    },
    {
      "id": 2,
      "name": "意外的慰藉",
      "desc": "他在一家深夜咖啡馆遇见一位人类女子，她谈论着城市的夜色与孤独。与她相处的宁静时刻，让他暂时忘却了职责与血统带来的重负，感到一种久违的完整。"
    },
    {
      "id": 3,
      "name": "血统的召唤",
      "desc": "家族长老秘密召见，提醒他不可忘记自己的根源，并暗示近期有重要同胞需要‘处理’。荣耀与背叛的古老训诫，像锁链般再次收紧。"
    },
    {
      "id": 4,
      "name": "任务的面孔",
      "desc": "最新的猎杀目标资料下达，照片上是他熟识的一位年轻异族，曾天真地向往人类世界。主角握着档案的手微微颤抖，命令与同情在心中无声角力。"
    },
    {
      "id": 5,
      "name": "夜晚的职责",
      "desc": "在潮湿的后巷，他找到了目标。对方认出他的血统，眼中充满被背叛的震惊与哀求。主角完成了任务，但归途中在路灯下反复擦拭双手，感到荣耀已变成污渍。"
    },
    {
      "id": 6,
      "name": "爱人的疑虑",
      "desc": "爱人察觉到他日益加深的沉默与疏离，询问他是否被噩梦困扰。他想倾诉一切，但双重身份筑起的高墙让他只能给出模糊的安慰，距离在亲密中悄然生长。"
    },
    {
      "id": 7,
      "name": "边界的溶解",
      "desc": "敌对势力——人类极端清剿部队——开始怀疑守夜者内部有异族渗透，展开秘密调查。主角同时受到来自人类同僚的审视与家族迫使其传递情报的压力，夹缝日益狭窄。"
    },
    {
      "id": 8,
      "name": "不可选的抉择",
      "desc": "为保护爱人免遭清剿部队伤害，主角不得不动用异族力量，导致身份暴露。他站在人类与家族之间，双方都视他为叛徒，他竭力维护的和平假象与个人荣耀彻底粉碎。"
    },
    {
      "id": 9,
      "name": "余烬的看守",
      "desc": "城市恢复了表面的平静，清剿行动暂停，家族也暂时隐匿。主角失去了所有位置，独自生活在城市边缘。他仍会在夜晚醒来，看守着这片他用一切换来、却再也无法属于他的寂静，荣耀已成灰烬。"
    }
  ],
  "tension_curve": [
    0.2,
    0.3,
    0.4,
    0.5,
    0.6,
    0.65,
    0.7,
    0.8,
    0.75
  ],
  "themes": [
    "身份认同",
    "忠诚与背叛",
    "爱的代价",
    "和平的虚伪性"
  ]
}