{
  "id": "sk_472",
  "archetype": "替代者",
  "title": "替身御史",
  "logline": "一名冒名顶替的御史，在调查一桩旧案时，发现自己正被卷入一场针对其真实身份的致命清算。",
  "style_tags": [
    "古代",
    "悬疑",
    "心理",
    "伦理"
  ],
  "ending": "bittersweet",
  "stakes": "真相",
  "actors": [
    "主角",
    "反派",
    "导师",
    "盟友",
    "爱人",
    "家族",
    "敌对势力"
  ],
  "beats": [
    {
      "id": 1,
      "name": "窃取的身份",
      "desc": "寒门书生李默为求活路，顶替了意外身亡的年轻御史王砚的身份。他战战兢兢踏入官场，凭借过目不忘的才能与谨小慎微，竟在御史台初步站稳脚跟。"
    },
    {
      "id": 2,
      "name": "旧案重启",
      "desc": "一桩涉及地方豪强与朝中官员的旧案被重新提起，李默被指派为主审。他很快发现，此案线索直指王砚的过去，而自己正被一双看不见的眼睛严密监视。"
    },
    {
      "id": 3,
      "name": "导师的警告",
      "desc": "御史台一位退隐的老前辈（曾是王砚的引路人）私下找到李默，暗示他身份可能早已暴露，并警告他旧案背后水极深，劝他及早抽身。"
    },
    {
      "id": 4,
      "name": "盟友与裂隙",
      "desc": "李默在查案中结识了一位正直却不得志的底层官吏，两人结为盟友。但随着调查深入，盟友开始对李默某些‘记忆缺失’产生怀疑，信任出现裂痕。"
    },
    {
      "id": 5,
      "name": "爱人的试探",
      "desc": "王砚的未婚妻，一位聪慧的世家小姐，察觉到李默言行中的细微差异。她怀着复杂的情感接近、试探，让李默在愧疚与动心中备受煎熬。"
    },
    {
      "id": 6,
      "name": "家族的重压",
      "desc": "王砚背后的家族势力（曾因王砚的‘死亡’而沉寂）似乎也嗅到了异常，开始以家族利益为名，向李默施加压力，要求他利用御史身份办特定的事。"
    },
    {
      "id": 7,
      "name": "敌手的围剿",
      "desc": "旧案背后的敌对势力（一个盘根错节的利益集团）确认了李默的‘虚假’，但他们不急于揭穿，而是设下圈套，意图让他以‘王砚’之名身败名裂，并永远闭嘴。"
    },
    {
      "id": 8,
      "name": "真相的代价",
      "desc": "李默在盟友和爱人的帮助下，险险破局，揭开了旧案的部分真相，也知晓了王砚当年‘意外’死亡的隐秘。但他冒名顶替之事也因此暴露在阳光之下。"
    },
    {
      "id": 9,
      "name": "身份的归还",
      "desc": "李默选择向有限的关键人物坦白，并承担罪责。他失去了官职与‘王砚’的一切，但保住了良知与爱人的理解。他带着一个不属于自己的秘密和一段无法公之于众的功绩，以‘李默’之名，默默离开京城。"
    }
  ],
  "tension_curve": [
    0.3,
    0.5,
    0.6,
    0.7,
    0.75,
    0.8,
    0.9,
    0.95,
    0.6
  ],
  "themes": [
    "身份认同",
    "罪与罚",
    "真相的重量",
    "个人与系统"
  ]
}